[{
     "OrderNumber": "10001",
     "ClientTag": "A101,8",
     "OrderDate": "11/20/2017",
     "OrderAmount": "500.00",
     "OrderStatus": "Принят",
     "OrderDirection": "give",
     "Payment": "cash",
     "OrderDescription": "Ставлю нал доллар на свой баланс",
     "Address": "Ap #897-1459 Quam Avenue",
     "Comment": "Коментарий"
     },
	{
     "OrderNumber": "10002",
     "ClientTag": "A101,8",
     "OrderDate": "11/20/2017",
     "OrderAmount": "500.00",
     "OrderStatus": "Завершен",
     "OrderDirection": "give",
     "Payment": "cash",
     "OrderDescription": "Ставлю  безнал на свой баланс",
     "Address": "Ap #897-1459 Quam Avenue",
     "Comment": "Коментарий"
     },
     {
     "OrderNumber": "10003",
     "ClientTag": "A101,8",
     "OrderDate": "11/21/2017",
     "OrderAmount": "500.00",
     "OrderStatus": "В обработке",
     "OrderDirection": "give",
     "Payment": "cash",
     "OrderDescription": "Ставлю гривну на свой баланс",
     "Address": "Ap #897-1459 Quam Avenue",
     "Comment": "Коментарий"
     },
     {
     "OrderNumber": "10003",
     "ClientTag": "A101,8",
     "OrderDate": "11/22/2017",
     "OrderAmount": "500.00",
     "OrderStatus": "В обработке",
     "OrderDirection": "give",
     "Payment": "cash",
     "OrderDescription": "Ставлю гривну на свой баланс",
     "Address": "Ap #897-1459 Quam Avenue",
     "Comment": "Коментарий"
     },
     {
     "OrderNumber": "10003",
     "ClientTag": "A101,8",
     "OrderDate": "11/23/2017",
     "OrderAmount": "500.00",
     "OrderStatus": "В обработке",
     "OrderDirection": "give",
     "Payment": "cash",
     "OrderDescription": "Ставлю гривну на свой баланс",
     "Address": "Ap #897-1459 Quam Avenue",
     "Comment": "Коментарий"
     },
     {
     "OrderNumber": "10003",
     "ClientTag": "A101,8",
     "OrderDate": "11/24/2017",
     "OrderAmount": "500.00",
     "OrderStatus": "В обработке",
     "OrderDirection": "give",
     "Payment": "cash",
     "OrderDescription": "Ставлю гривну на свой баланс",
     "Address": "Ap #897-1459 Quam Avenue",
     "Comment": "Коментарий"
     },
     {
     "OrderNumber": "10004",
     "ClientTag": "A101,8",
     "OrderDate": "11/25/2017",
     "OrderAmount": "1500.00",
     "OrderStatus": "Принят",
     "OrderDirection": "give",
     "Payment": "cash",
     "OrderDescription": "Ставлю нал доллар на свой баланс",
     "Address": "Ap #897-1459 Quam Avenue",
     "Comment": "Коментарий"
     },
     {
     "OrderNumber": "1012345",
     "ClientTag": "A101,8",
     "OrderDate": "11/25/2017",
     "OrderAmount": "2390.00",
     "OrderStatus": "Завершен",
     "OrderDirection": "give",
     "Payment": "cash",
     "OrderDescription": "Ставлю нал доллар на свой баланс",
     "Address": "Ap #897-1459 Quam Avenue",
     "Comment": "Коментарий"
     }]
